{"ver":"0.1","info":{"id":"4tjGWG","date":"1431969463","viewed":625,"name":"Uniform Height","username":"fleegle2000","description":"Takes an image and removes height information such that a 1-pixel band across the image expands to fill vertical space. This is meant to visualize how the image would look like to a 2-dimensional being if the image center intersected the 2d world.","likes":0,"published":1,"flags":0,"tags":[]},"renderpass":[{"inputs":[{"id":"4dfGRn","filepath":"/media/a/8de3a3924cb95bd0e95a443fff0326c869f9d4979cd1d5b6e94e2a01f5be53e9.jpg","previewfilepath":"/media/ap/8de3a3924cb95bd0e95a443fff0326c869f9d4979cd1d5b6e94e2a01f5be53e9.jpg","type":"texture","channel":0,"sampler":{"filter":"mipmap","wrap":"repeat","vflip":"false","srgb":"false","internal":"byte"},"published":1}],"outputs":[],"code":"// Uniform height shader\nvoid mainImage( out vec4 fragColor, in vec2 fragCoord ) {\n\tvec2 uv = (fragCoord.xy / iResolution.xy)*1.0 - vec2(1.0);\n    fragColor = texture(iChannel0, vec2(1.0+uv.x, 0.5));\n}","name":"","description":"","type":"image"}]}