{"ver":"0.1","info":{"id":"ldBBDt","date":"1502714544","viewed":132,"name":"Specular material - 88 chars","username":"PrzemyslawZaworski","description":"It looks like synthetic material with specular highlights. ","likes":2,"published":1,"flags":0,"tags":[]},"renderpass":[{"inputs":[{"id":"XdX3Rn","filepath":"/media/a/52d2a8f514c4fd2d9866587f4d7b2a5bfa1a11a0e772077d7682deb8b3b517e5.jpg","previewfilepath":"/media/ap/52d2a8f514c4fd2d9866587f4d7b2a5bfa1a11a0e772077d7682deb8b3b517e5.jpg","type":"texture","channel":0,"sampler":{"filter":"mipmap","wrap":"repeat","vflip":"true","srgb":"false","internal":"byte"},"published":1}],"outputs":[{"id":"4dfGRr","channel":0}],"code":"#define mainImage(c,f) c=texture(iChannel0,mix(f/iResolution.xy,abs(sin(f)),abs(cos(f))))","name":"Image","description":"","type":"image"}]}