{"ver": "0.1", "info": {"id": "MttcWj", "date": "1534178225", "viewed": 346, "name": "clamp and smoothstep function", "username": "thinkcg", "description": "paint two lines with clamp and smoothstep function", "likes": 3, "published": 1, "flags": 0, "tags": ["lamp"], "requires": ["imagebuf"]}, "renderpass": [{"inputs": [], "outputs": [{"id": "4dfGRr", "channel": 0}], "code": "/*vec4 circle(vec2 uv,vec2 pos,float rad,vec3 color)\n{\n \tfloat cha = length(uv-pos) - rad;\n    return vec4(color,1.0 - cha);\n}*/\nvoid mainImage( out vec4 fragColor, in vec2 fragCoord )\n{\n    // Normalized pixel coordinates (from 0 to 1)\n    vec2 uv = fragCoord/iResolution.xy;\n\t//smoothstep\u56fe\u5c42\n\tvec4 layer1;\n       float y = smoothstep(0.0,1.0,uv.x);\n       float dis = length(y-uv.y);\n       if(dis<0.005)\n       \tlayer1 = vec4(1,0,0,1);\n    else\n        layer1 = vec4(0,0,0,0);\n    // clamp\u56fe\u5c42\n    vec4 layer2;\n    float clampY = clamp(uv.x,0.0,1.0);\n    float clampDis = length(clampY-uv.y);\n    float t = 1.0 - step(0.005,clampDis);\n    layer2 = vec4(0,t,0,t);\n    \n    \n    fragColor = mix(layer1,layer2,layer2.a);  \t   \n    //fragColor = vec4(iMouse.y/100.0,0,0,1);//iMouse\u5206\u91cf\u53d6\u503c\u8303\u56f40-\u7a97\u53e3\u5c3a\u5bf8\uff0c\u539f\u70b9\u5728\u5de6\u4e0b\u89d2\n}", "name": "Image", "description": "", "type": "image"}]}